custom_otello_linter/__init__.py
custom_otello_linter/config.py
custom_otello_linter/plugins.py
custom_otello_linter/abstract_checkers/__init__.py
custom_otello_linter/abstract_checkers/scenario_checker.py
custom_otello_linter/abstract_checkers/scenario_helper.py
custom_otello_linter/abstract_checkers/step_checker.py
custom_otello_linter/errors/__init__.py
custom_otello_linter/errors/errors.py
custom_otello_linter/helpers/__init__.py
custom_otello_linter/helpers/get_full_func_name.py
custom_otello_linter/helpers/get_init_step.py
custom_otello_linter/helpers/get_make_screenshot_calls.py
custom_otello_linter/types/__init__.py
custom_otello_linter/types/types.py
custom_otello_linter/visitors/__init__.py
custom_otello_linter/visitors/_visitor_with_filename.py
custom_otello_linter/visitors/scenario_visitor.py
custom_otello_linter/visitors/scenario_and_steps_checkers/__init__.py
custom_otello_linter/visitors/scenario_and_steps_checkers/screenshot_label_and_func_checker.py
custom_otello_linter/visitors/scenario_checkers/__init__.py
custom_otello_linter/visitors/scenario_checkers/decorator_vedro_params_checker.py
custom_otello_linter/visitors/steps_checkers/__init__.py
custom_otello_linter/visitors/steps_checkers/make_screenshot_checker.py
custom_otello_linter/visitors/steps_checkers/platform_usage_checker.py
custom_otello_linter-1.0.5.dist-info/LICENSE
custom_otello_linter-1.0.5.dist-info/METADATA
custom_otello_linter-1.0.5.dist-info/WHEEL
custom_otello_linter-1.0.5.dist-info/entry_points.txt
custom_otello_linter-1.0.5.dist-info/top_level.txt
custom_otello_linter-1.0.5.dist-info/RECORD
