Metadata-Version: 2.1
Name: custom-otello-linter
Version: 1.0.5
Summary: flake8 based linter for frontend tests
Home-page: https://github.com/iri6e4k0/custom-otello-linter
Author: Irina
Author-email: iri6e4ko@gmail.com
License: Apache-2.0
Classifier: License :: OSI Approved :: Apache Software License
Classifier: Programming Language :: Python :: 3.10
Classifier: Programming Language :: Python :: 3.11
Requires-Python: >=3.10
License-File: LICENSE
Requires-Dist: flake8<7.0,>=6.0
Requires-Dist: flake8-plugin-utils<2.0,>=1.3.2
